tingetone/__init__.py
tingetone/color_print.py
tingetone/fore.py
tingetone/specials.py
tingetone/utils.py
tingetone-0.0.2.dist-info/LICENSE
tingetone-0.0.2.dist-info/METADATA
tingetone-0.0.2.dist-info/WHEEL
tingetone-0.0.2.dist-info/top_level.txt
tingetone-0.0.2.dist-info/RECORD
