Metadata-Version: 2.1
Name: tingetone
Version: 0.0.2
Summary: ANSI color formatting for output in terminal
Author: Kim Yung
License: MIT
Classifier: License :: OSI Approved :: MIT License
Classifier: Programming Language :: Python
Classifier: Programming Language :: Python :: 3
Classifier: Environment :: Console
Classifier: Operating System :: OS Independent
Classifier: Topic :: Terminals
Classifier: Topic :: Text Processing
Classifier: Topic :: Utilities
Requires-Python: >=3.5
License-File: LICENSE
